{
    "m_GameObject": {
        "m_FileID": 0,
        "m_PathID": 0
    },
    "m_Enabled": 1,
    "m_Script": {
        "m_FileID": 0,
        "m_PathID": -5527745578678275596
    },
    "m_Name": "EQ_KODAI_01_05_b_2d",
    "QuestID": "",
    "mSequences": [
        {
            "UnitName": "",
            "Percentage": 0,
            "Turn": 0,
            "GridXY": "",
            "RestHP": "",
            "SkillTiming": 0,
            "TargetSkill": "",
            "TargetUnit": "",
            "IsFirstOnly": 0,
            "SkillElem": 0,
            "SkillCond": 1,
            "Trigger": 0,
            "Actions": [
                {
                    "m_FileID": 0,
                    "m_PathID": 678649519988708931
                },
                {
                    "m_FileID": 0,
                    "m_PathID": -3583253744854546278
                },
                {
                    "m_FileID": 0,
                    "m_PathID": -2576568928357490114
                },
                {
                    "m_FileID": 0,
                    "m_PathID": 1948413742672059170
                },
                {
                    "m_FileID": 0,
                    "m_PathID": -9198680259114880521
                },
                {
                    "m_FileID": 0,
                    "m_PathID": 7617540885050178405
                },
                {
                    "m_FileID": 0,
                    "m_PathID": -8443404944118741345
                },
                {
                    "m_FileID": 0,
                    "m_PathID": 6733384099233373452
                },
                {
                    "m_FileID": 0,
                    "m_PathID": -300270182032375772
                },
                {
                    "m_FileID": 0,
                    "m_PathID": -6562740050153238908
                },
                {
                    "m_FileID": 0,
                    "m_PathID": -1829885048123858444
                },
                {
                    "m_FileID": 0,
                    "m_PathID": 6332883913203053467
                },
                {
                    "m_FileID": 0,
                    "m_PathID": -2296434940235777362
                },
                {
                    "m_FileID": 0,
                    "m_PathID": -544629073059945590
                },
                {
                    "m_FileID": 0,
                    "m_PathID": 3762123781083416507
                },
                {
                    "m_FileID": 0,
                    "m_PathID": 6218963748825230828
                },
                {
                    "m_FileID": 0,
                    "m_PathID": -4908629637436014181
                },
                {
                    "m_FileID": 0,
                    "m_PathID": -6006121529302588189
                },
                {
                    "m_FileID": 0,
                    "m_PathID": 5560913575948499374
                },
                {
                    "m_FileID": 0,
                    "m_PathID": 2682195802188653234
                },
                {
                    "m_FileID": 0,
                    "m_PathID": 4554913608975270114
                },
                {
                    "m_FileID": 0,
                    "m_PathID": -3442381868767976906
                },
                {
                    "m_FileID": 0,
                    "m_PathID": -390246616970356465
                },
                {
                    "m_FileID": 0,
                    "m_PathID": -4550366260028052912
                },
                {
                    "m_FileID": 0,
                    "m_PathID": -7811654435398149987
                },
                {
                    "m_FileID": 0,
                    "m_PathID": -4534054531402055443
                },
                {
                    "m_FileID": 0,
                    "m_PathID": 636173215538172753
                },
                {
                    "m_FileID": 0,
                    "m_PathID": -3305152486912366215
                },
                {
                    "m_FileID": 0,
                    "m_PathID": 4323623564110414480
                },
                {
                    "m_FileID": 0,
                    "m_PathID": 6174230802218683583
                },
                {
                    "m_FileID": 0,
                    "m_PathID": -1222232559509674321
                },
                {
                    "m_FileID": 0,
                    "m_PathID": 3005643271019766146
                },
                {
                    "m_FileID": 0,
                    "m_PathID": 4322804480479856253
                },
                {
                    "m_FileID": 0,
                    "m_PathID": 3214976723806738845
                },
                {
                    "m_FileID": 0,
                    "m_PathID": -4410446358562516896
                },
                {
                    "m_FileID": 0,
                    "m_PathID": -5712797639189357549
                },
                {
                    "m_FileID": 0,
                    "m_PathID": 1761158204584700488
                },
                {
                    "m_FileID": 0,
                    "m_PathID": 4759518732841059703
                },
                {
                    "m_FileID": 0,
                    "m_PathID": -4982928306641284679
                },
                {
                    "m_FileID": 0,
                    "m_PathID": -348702274395400220
                },
                {
                    "m_FileID": 0,
                    "m_PathID": -6568283903560394693
                },
                {
                    "m_FileID": 0,
                    "m_PathID": 5928775182581130722
                },
                {
                    "m_FileID": 0,
                    "m_PathID": -7150933031434155238
                },
                {
                    "m_FileID": 0,
                    "m_PathID": 6505060407170464704
                },
                {
                    "m_FileID": 0,
                    "m_PathID": 5552286617070894533
                },
                {
                    "m_FileID": 0,
                    "m_PathID": 5071478903021941602
                },
                {
                    "m_FileID": 0,
                    "m_PathID": -7078424177413244854
                },
                {
                    "m_FileID": 0,
                    "m_PathID": 3520117382148442479
                },
                {
                    "m_FileID": 0,
                    "m_PathID": 8053185800056910560
                },
                {
                    "m_FileID": 0,
                    "m_PathID": 5177149863286379141
                },
                {
                    "m_FileID": 0,
                    "m_PathID": -2372992636278880735
                },
                {
                    "m_FileID": 0,
                    "m_PathID": 9214510526722401855
                },
                {
                    "m_FileID": 0,
                    "m_PathID": -1602268230808409381
                },
                {
                    "m_FileID": 0,
                    "m_PathID": -6009855219734329621
                },
                {
                    "m_FileID": 0,
                    "m_PathID": 32602729147538668
                },
                {
                    "m_FileID": 0,
                    "m_PathID": -2657795709423488631
                },
                {
                    "m_FileID": 0,
                    "m_PathID": 8376801117657610635
                },
                {
                    "m_FileID": 0,
                    "m_PathID": -2605919767656813094
                },
                {
                    "m_FileID": 0,
                    "m_PathID": 5645696127140543833
                },
                {
                    "m_FileID": 0,
                    "m_PathID": 1540448202336962092
                },
                {
                    "m_FileID": 0,
                    "m_PathID": -5644761216734521654
                },
                {
                    "m_FileID": 0,
                    "m_PathID": 1922496556879511441
                },
                {
                    "m_FileID": 0,
                    "m_PathID": -4108316710124424702
                },
                {
                    "m_FileID": 0,
                    "m_PathID": 8299462692073829832
                },
                {
                    "m_FileID": 0,
                    "m_PathID": 8980499614056660009
                },
                {
                    "m_FileID": 0,
                    "m_PathID": 2656817958327738919
                },
                {
                    "m_FileID": 0,
                    "m_PathID": 1804438257024504913
                },
                {
                    "m_FileID": 0,
                    "m_PathID": 2981565426743311456
                },
                {
                    "m_FileID": 0,
                    "m_PathID": -8817638019084524115
                }
            ]
        }
    ]
}