{
    "m_GameObject": {
        "m_FileID": 0,
        "m_PathID": 0
    },
    "m_Enabled": 1,
    "m_Script": {
        "m_FileID": 0,
        "m_PathID": 7110536906776067005
    },
    "m_Name": "QE02_1_1_04_a_3d",
    "QuestID": "",
    "mSequences": [
        {
            "UnitName": "",
            "Percentage": 0,
            "Turn": 0,
            "GridXY": "",
            "RestHP": "",
            "SkillTiming": 0,
            "TargetSkill": "",
            "TargetUnit": "",
            "IsFirstOnly": 0,
            "SkillElem": 0,
            "SkillCond": 1,
            "Trigger": 0,
            "Actions": [
                {
                    "m_FileID": 0,
                    "m_PathID": 7159346655600315191
                },
                {
                    "m_FileID": 0,
                    "m_PathID": 6042678541475310130
                },
                {
                    "m_FileID": 0,
                    "m_PathID": 493076107011487681
                },
                {
                    "m_FileID": 0,
                    "m_PathID": 7943708538070249002
                },
                {
                    "m_FileID": 0,
                    "m_PathID": 244494780337191598
                },
                {
                    "m_FileID": 0,
                    "m_PathID": -1018556946831705328
                },
                {
                    "m_FileID": 0,
                    "m_PathID": -4902843921985267800
                }
            ]
        }
    ]
}