{
    "m_GameObject": {
        "m_FileID": 0,
        "m_PathID": 0
    },
    "m_Enabled": 1,
    "m_Script": {
        "m_FileID": 0,
        "m_PathID": -5527745578678275596
    },
    "m_Name": "QE03_4_1_03_a_2d",
    "QuestID": "",
    "mSequences": [
        {
            "UnitName": "",
            "Percentage": 0,
            "Turn": 0,
            "GridXY": "",
            "RestHP": "",
            "SkillTiming": 0,
            "TargetSkill": "",
            "TargetUnit": "",
            "IsFirstOnly": 0,
            "SkillElem": 0,
            "SkillCond": 1,
            "Trigger": 0,
            "Actions": [
                {
                    "m_FileID": 0,
                    "m_PathID": 1727502498063822931
                },
                {
                    "m_FileID": 0,
                    "m_PathID": 1016464315628388930
                },
                {
                    "m_FileID": 0,
                    "m_PathID": -6699939850570606628
                },
                {
                    "m_FileID": 0,
                    "m_PathID": 2888087870653603364
                },
                {
                    "m_FileID": 0,
                    "m_PathID": -1400358736812520596
                },
                {
                    "m_FileID": 0,
                    "m_PathID": 7839262562198665956
                },
                {
                    "m_FileID": 0,
                    "m_PathID": -496455648813971766
                },
                {
                    "m_FileID": 0,
                    "m_PathID": 942403923190549233
                },
                {
                    "m_FileID": 0,
                    "m_PathID": 6757098256465480031
                },
                {
                    "m_FileID": 0,
                    "m_PathID": 8890466671292012429
                },
                {
                    "m_FileID": 0,
                    "m_PathID": 889404878258482118
                },
                {
                    "m_FileID": 0,
                    "m_PathID": -2697349016634121036
                },
                {
                    "m_FileID": 0,
                    "m_PathID": 6300111510271860614
                },
                {
                    "m_FileID": 0,
                    "m_PathID": -9028256034090249314
                },
                {
                    "m_FileID": 0,
                    "m_PathID": -3782148805007779121
                },
                {
                    "m_FileID": 0,
                    "m_PathID": 5704637622040163448
                },
                {
                    "m_FileID": 0,
                    "m_PathID": -5547309578837769272
                },
                {
                    "m_FileID": 0,
                    "m_PathID": -8827500012948694247
                },
                {
                    "m_FileID": 0,
                    "m_PathID": 189184827584257520
                },
                {
                    "m_FileID": 0,
                    "m_PathID": 7578470995315869924
                },
                {
                    "m_FileID": 0,
                    "m_PathID": -8404922550266937793
                },
                {
                    "m_FileID": 0,
                    "m_PathID": 7934338286727213698
                },
                {
                    "m_FileID": 0,
                    "m_PathID": -6564439243458685140
                },
                {
                    "m_FileID": 0,
                    "m_PathID": 5458989132426352263
                },
                {
                    "m_FileID": 0,
                    "m_PathID": -2384224791835627560
                },
                {
                    "m_FileID": 0,
                    "m_PathID": 865984993756270098
                },
                {
                    "m_FileID": 0,
                    "m_PathID": -7413341606859913200
                },
                {
                    "m_FileID": 0,
                    "m_PathID": 4390385171424275442
                },
                {
                    "m_FileID": 0,
                    "m_PathID": -4853456903312426834
                },
                {
                    "m_FileID": 0,
                    "m_PathID": 2096755642169903036
                },
                {
                    "m_FileID": 0,
                    "m_PathID": -8698418957021669733
                },
                {
                    "m_FileID": 0,
                    "m_PathID": -7967621968437949778
                },
                {
                    "m_FileID": 0,
                    "m_PathID": -8065598963754020066
                },
                {
                    "m_FileID": 0,
                    "m_PathID": -1430887983701841096
                },
                {
                    "m_FileID": 0,
                    "m_PathID": -7185235165865885378
                },
                {
                    "m_FileID": 0,
                    "m_PathID": 6982463084579578333
                },
                {
                    "m_FileID": 0,
                    "m_PathID": -1409617657982020537
                },
                {
                    "m_FileID": 0,
                    "m_PathID": -7667236477392354681
                },
                {
                    "m_FileID": 0,
                    "m_PathID": 5613638090059233997
                },
                {
                    "m_FileID": 0,
                    "m_PathID": 3167364524913332932
                },
                {
                    "m_FileID": 0,
                    "m_PathID": 4033663964530050758
                },
                {
                    "m_FileID": 0,
                    "m_PathID": -206937958129090433
                },
                {
                    "m_FileID": 0,
                    "m_PathID": -2158579358833109055
                },
                {
                    "m_FileID": 0,
                    "m_PathID": -2311024427627814466
                },
                {
                    "m_FileID": 0,
                    "m_PathID": -148885581403029957
                },
                {
                    "m_FileID": 0,
                    "m_PathID": 3735988226812909926
                },
                {
                    "m_FileID": 0,
                    "m_PathID": -5513169612302476279
                },
                {
                    "m_FileID": 0,
                    "m_PathID": 1987495785630669187
                },
                {
                    "m_FileID": 0,
                    "m_PathID": 6375995997605754598
                },
                {
                    "m_FileID": 0,
                    "m_PathID": 912551351740666009
                },
                {
                    "m_FileID": 0,
                    "m_PathID": 2553712289054220472
                },
                {
                    "m_FileID": 0,
                    "m_PathID": -2112352651404229227
                },
                {
                    "m_FileID": 0,
                    "m_PathID": -2762924530976833747
                },
                {
                    "m_FileID": 0,
                    "m_PathID": -6504081654317988728
                },
                {
                    "m_FileID": 0,
                    "m_PathID": -2739060328997834231
                },
                {
                    "m_FileID": 0,
                    "m_PathID": -1572861349321864842
                },
                {
                    "m_FileID": 0,
                    "m_PathID": -8258618326043749204
                },
                {
                    "m_FileID": 0,
                    "m_PathID": -9006021417456633954
                },
                {
                    "m_FileID": 0,
                    "m_PathID": -4601369271749674727
                },
                {
                    "m_FileID": 0,
                    "m_PathID": 9163973784162728639
                },
                {
                    "m_FileID": 0,
                    "m_PathID": -4844888427831679240
                },
                {
                    "m_FileID": 0,
                    "m_PathID": 3978362103573988539
                },
                {
                    "m_FileID": 0,
                    "m_PathID": -3595745979962657525
                },
                {
                    "m_FileID": 0,
                    "m_PathID": 2269228720316493469
                },
                {
                    "m_FileID": 0,
                    "m_PathID": 6587030075304956897
                },
                {
                    "m_FileID": 0,
                    "m_PathID": -8005385887349009058
                },
                {
                    "m_FileID": 0,
                    "m_PathID": 3845844356180406895
                },
                {
                    "m_FileID": 0,
                    "m_PathID": 8986323340929938161
                },
                {
                    "m_FileID": 0,
                    "m_PathID": -3427650970740188571
                },
                {
                    "m_FileID": 0,
                    "m_PathID": 7166189672902591562
                },
                {
                    "m_FileID": 0,
                    "m_PathID": 6900266296990657125
                },
                {
                    "m_FileID": 0,
                    "m_PathID": 1857799066981369801
                },
                {
                    "m_FileID": 0,
                    "m_PathID": -7275019623398783535
                },
                {
                    "m_FileID": 0,
                    "m_PathID": -592717082547301097
                },
                {
                    "m_FileID": 0,
                    "m_PathID": 3282704902467612595
                },
                {
                    "m_FileID": 0,
                    "m_PathID": -2446444500635604859
                },
                {
                    "m_FileID": 0,
                    "m_PathID": -5720874677836680103
                },
                {
                    "m_FileID": 0,
                    "m_PathID": -8393651810063024364
                },
                {
                    "m_FileID": 0,
                    "m_PathID": 7837402335079737330
                },
                {
                    "m_FileID": 0,
                    "m_PathID": 7497009393268187561
                },
                {
                    "m_FileID": 0,
                    "m_PathID": 8207673201564074814
                },
                {
                    "m_FileID": 0,
                    "m_PathID": -5670790533937976029
                },
                {
                    "m_FileID": 0,
                    "m_PathID": 2844348225435031701
                },
                {
                    "m_FileID": 0,
                    "m_PathID": 3439782749989351449
                },
                {
                    "m_FileID": 0,
                    "m_PathID": 5395802563125460669
                },
                {
                    "m_FileID": 0,
                    "m_PathID": 6202049444843982936
                },
                {
                    "m_FileID": 0,
                    "m_PathID": 2862631517014333952
                },
                {
                    "m_FileID": 0,
                    "m_PathID": -2747204063459400066
                },
                {
                    "m_FileID": 0,
                    "m_PathID": -7927964645548441106
                },
                {
                    "m_FileID": 0,
                    "m_PathID": 1331429186198919050
                },
                {
                    "m_FileID": 0,
                    "m_PathID": -4672710090507695224
                },
                {
                    "m_FileID": 0,
                    "m_PathID": -4033725500323995790
                },
                {
                    "m_FileID": 0,
                    "m_PathID": 8995587322331529457
                },
                {
                    "m_FileID": 0,
                    "m_PathID": 7544714510854632430
                },
                {
                    "m_FileID": 0,
                    "m_PathID": -2495952905081589284
                },
                {
                    "m_FileID": 0,
                    "m_PathID": -8270295107246820904
                },
                {
                    "m_FileID": 0,
                    "m_PathID": -1809044622851592856
                },
                {
                    "m_FileID": 0,
                    "m_PathID": 7920729731160730962
                },
                {
                    "m_FileID": 0,
                    "m_PathID": 2412289633336653001
                },
                {
                    "m_FileID": 0,
                    "m_PathID": 3637499191429154964
                },
                {
                    "m_FileID": 0,
                    "m_PathID": 128339250258864534
                },
                {
                    "m_FileID": 0,
                    "m_PathID": 2520044394469623000
                },
                {
                    "m_FileID": 0,
                    "m_PathID": -3019487944540601560
                },
                {
                    "m_FileID": 0,
                    "m_PathID": 9121881351364394233
                },
                {
                    "m_FileID": 0,
                    "m_PathID": -3457908142662481275
                },
                {
                    "m_FileID": 0,
                    "m_PathID": -5358467096212817327
                },
                {
                    "m_FileID": 0,
                    "m_PathID": 7570289628736246329
                },
                {
                    "m_FileID": 0,
                    "m_PathID": 8831079469682857035
                },
                {
                    "m_FileID": 0,
                    "m_PathID": -8831756372527936373
                }
            ]
        }
    ]
}